{"T1106: Native API": [18, 6, 6], "T1055: Process Injection": [93, 59, 53], "T1218: System Binary Proxy Execution": [92, 86, 84], "T1053: Scheduled Task/Job": [5, 4, 2], "T1056: Input Capture": [1, 1, 1], "T1059: Command and Scripting Interpreter": [95, 94, 92], "T1547: Boot or Logon Autostart Execution": [93, 30, 21], "T1036: Masquerading": [7, 7, 7], "T1070: Indicator Removal": [92, 34, 14], "T1574: Hijack Execution Flow": [10, 1, 1], "T1546: Event Triggered Execution": [16, 5, 3], "T1133: External Remote Services": [40, 35, 16], "T1021: Remote Services": [91, 85, 66], "T1105: Ingress Tool Transfer": [65, 64, 62], "T1586: Compromise Accounts": [2, 2, 2], "T1078: Valid Accounts": [13, 7, 6], "T1090: Proxy": [3, 2, 2], "T1221: Template Injection": [2, 2, 2], "T1204: User Execution": [66, 15, 7], "T1136: Create Account": [3, 3, 3], "T1548: Abuse Elevation Control Mechanism": [1, 0, 0], "T1134: Access Token Manipulation": [5, 2, 2], "T1037: Boot or Logon Initialization Scripts": [7, 4, 2], "T1124: System Time Discovery": [12, 4, 4], "T1529: System Shutdown/Reboot": [72, 3, 2], "T1559: Inter-Process Communication": [3, 2, 2], "T1570: Lateral Tool Transfer": [29, 15, 9], "T1135: Network Share Discovery": [80, 35, 10], "T1095: Non-Application Layer Protocol": [2, 1, 1], "T1005: Data from Local System": [52, 43, 8], "T1560: Archive Collected Data": [17, 1, 1], "T1027: Obfuscated Files or Information": [62, 59, 4], "T1114: Email Collection": [41, 11, 6], "T1025: Data from Removable Media": [3, 3, 3], "T1003: OS Credential Dumping": [46, 15, 4], "T1074: Data Staged": [8, 5, 2], "T1219: Remote Access Software": [36, 18, 14], "T1047: Windows Management Instrumentation": [95, 68, 65], "T1057: Process Discovery": [67, 54, 43], "T1087: Account Discovery": [94, 85, 83], "T1018: Remote System Discovery": [35, 27, 25], "T1082: System Information Discovery": [74, 10, 4], "T1069: Permission Groups Discovery": [99, 97, 97], "T1016: System Network Configuration Discovery": [67, 67, 62], "T1566: Phishing": [98, 65, 46], "T1497: Virtualization/Sandbox Evasion": [13, 7, 6], "T1518: Software Discovery": [4, 3, 3], "T1049: System Network Connections Discovery": [40, 14, 13], "T1490: Inhibit System Recovery": [2, 2, 2], "T1489: Service Stop": [35, 3, 2], "T1113: Screen Capture": [3, 2, 2], "T1041: Exfiltration Over C2 Channel": [5, 5, 5], "T1125: Video Capture": [1, 1, 1], "T1119: Automated Collection": [7, 7, 7], "T1115: Clipboard Data": [2, 2, 2], "T1083: File and Directory Discovery": [24, 19, 4], "T1564: Hide Artifacts": [2, 2, 2], "T1010: Application Window Discovery": [4, 2, 2], "T1543: Create or Modify System Process": [98, 97, 97], "T1033: System Owner/User Discovery": [58, 54, 53], "T1071: Application Layer Protocol": [77, 36, 11], "T1480: Execution Guardrails": [8, 1, 1], "T1496: Resource Hijacking": [4, 3, 3], "T1112: Modify Registry": [46, 27, 2], "T1132: Data Encoding": [19, 16, 2], "T1001: Data Obfuscation": [4, 4, 4], "T1573: Encrypted Channel": [5, 2, 2], "T1572: Protocol Tunneling": [2, 2, 2], "T1222: File and Directory Permissions Modification": [3, 3, 2], "T1110: Brute Force": [4, 4, 4], "T1553: Subvert Trust Controls": [1, 1, 1], "T1588: Obtain Capabilities": [3, 3, 3], "T1129: Shared Modules": [4, 2, 2], "T1620: Reflective Code Loading": [19, 12, 4], "T1561: Disk Wipe": [6, 1, 1], "T1485: Data Destruction": [11, 4, 3], "T1068: Exploitation for Privilege Escalation": [2, 2, 1], "T1608: Stage Capabilities": [6, 2, 2], "T1189: Drive-by Compromise": [2, 1, 1], "T1014: Rootkit": [7, 7, 7], "T1542: Pre-OS Boot": [3, 2, 2], "T1587: Develop Capabilities": [1, 1, 1], "T1123: Audio Capture": [1, 0, 0], "T1584: Compromise Infrastructure": [2, 2, 2], "T1190: Exploit Public-Facing Application": [6, 4, 4], "T1589: Gather Victim Identity Information": [2, 2, 1], "T1505: Server Software Component": [9, 5, 5], "T1539: Steal Web Session Cookie": [0, 0, 0], "T1185: Browser Session Hijacking": [3, 0, 0], "T1568: Dynamic Resolution": [2, 2, 2], "T1008: Fallback Channels": [18, 16, 15], "T1571: Non-Standard Port": [10, 6, 6], "T1552: Unsecured Credentials": [5, 5, 5], "T1555: Credentials from Password Stores": [2, 2, 2], "T1091: Replication Through Removable Media": [1, 1, 0], "T1486: Data Encrypted for Impact": [98, 91, 34], "T1140: Deobfuscate/Decode Files or Information": [50, 43, 31], "T1562: Impair Defenses": [7, 5, 3], "T1482: Domain Trust Discovery": [81, 77, 67], "T1098: Account Manipulation": [5, 5, 5], "T1569: System Services": [99, 97, 97], "T1007: System Service Discovery": [7, 7, 7], "T1622: Debugger Evasion": [5, 5, 5], "T1012: Query Registry": [2, 1, 1], "T1203: Exploitation for Client Execution": [5, 5, 3], "T1120: Peripheral Device Discovery": [6, 6, 6], "T1020: Automated Exfiltration": [14, 14, 14], "T1217: Browser Bookmark Discovery": [1, 1, 1], "T1029: Scheduled Transfer": [4, 2, 2], "T1595: Active Scanning": [17, 2, 2], "T1614: System Location Discovery": [1, 1, 1], "T1585: Establish Accounts": [2, 1, 1], "T1210: Exploitation of Remote Services": [18, 18, 18], "T1567: Exfiltration Over Web Service": [58, 20, 8], "T1048: Exfiltration Over Alternative Protocol": [10, 5, 5], "T1583: Acquire Infrastructure": [7, 1, 1], "T1550: Use Alternate Authentication Material": [3, 3, 3], "T1558: Steal or Forge Kerberos Tickets": [1, 1, 1], "T1102: Web Service": [5, 5, 5], "T1046: Network Service Discovery": [11, 4, 4]}